{
  "movies": [
    {
      "title": "Kill bill",
      "rating": "5",
      "id": 9
    },
    {
      "title": "Fight Club",
      "rating": "5",
      "id": 10
    },
    {
      "title": "Spirited Away",
      "rating": "5",
      "id": 12
    },
    {
      "title": "IT",
      "rating": "5",
      "id": 13
    },
    {
      "title": "Jurassic Park",
      "rating": "5",
      "id": 15
    },
    {
      "title": "Rocky",
      "rating": "5",
      "id": 16
    },
    {
      "title": "Beauty and the Beast",
      "rating": "4",
      "id": 19
    },
    {
      "title": "Cowboy Bebop",
      "rating": "4",
      "id": 20
    }
  ]
}